[
  {
    "_comment": "This is an example for a Reference object. The csl_data field contains Citation Style Language (CSL) JSON format citation metadata.",
    "id": "SMITH-2020-EXP",
    "study_type": "Experiment",
    "comp_type": "Example Component Type Description",
    "pdf_saved": "True",
    "csl_data": {
      "type": "article-journal",
      "id": "SMITH-2020-EXP",
      "title": "Example Study Title",
      "author": [
        {"family": "Smith", "given": "John"},
        {"family": "Doe", "given": "Jane"}
      ],
      "issued": {"date-parts": [[2020]]},
      "DOI": "https://doi.org/10.1234/example.doi",
      "URL": "https://example.com/paper"
    }
  }
]
